mdocspoofer/__init__.py
mdocspoofer/_version.py
mdocspoofer/mdoc.py
mdocspoofer/version.py
mdocspoofer-0.0.8.dist-info/LICENSE.txt
mdocspoofer-0.0.8.dist-info/METADATA
mdocspoofer-0.0.8.dist-info/WHEEL
mdocspoofer-0.0.8.dist-info/entry_points.txt
mdocspoofer-0.0.8.dist-info/top_level.txt
mdocspoofer-0.0.8.dist-info/RECORD
